{"license":"CC0-1.0","description":{"sv":"Flyttblock"},"sources":"Naturvårdsverket (Swedish Environmental Protection Agency), https://metadatakatalogen.naturvardsverket.se/metadatakatalogen/GetMetaDataById?id=c6b02e88-8084-4b3f-8a7d-33e5d45349c4","zoom":13,"latitude":59.95269010676114,"longitude":13.265722435260585,"data":{"type":"Feature","properties":{"NVRID":"2003848","NAMN":"Flyttblock","SKYDDSTYP":"Naturminne","BESLSTATUS":"Gällande","URSBESLDAT":"1928/07/28","URSGALLDAT":"1928/07/28","SENGALLDAT":"1928/07/28","LAN":"Värmlands Län","KOMMUN":"Sunne","FORVALTARE":"Länsstyrelsen i Värmlands län","AREA_HA":0.03,"LAND_HA":0.03,"VATTEN_HA":0,"SKOG_HA":0,"GEOSTATUS":"Ospecificerad","DIARIENR":"95-1117-1927, N:O 1413, Rr 3","LAGRUM":"Lag om naturminnesmärken från 1909","BESLMYND":"Länsstyrelse"},"geometry":{"type":"MultiPolygon","coordinates":[[[[13.265564026060158,59.952756648789],[13.26587019405203,59.95276255062408],[13.265880840768844,59.95262356005372],[13.265574673587276,59.95261766722407],[13.265564026060158,59.952756648789]]]]}}}