{"license":"CC0-1.0","description":{"sv":"Hovsjö 1:1"},"sources":"Naturvårdsverket (Swedish Environmental Protection Agency), https://metadatakatalogen.naturvardsverket.se/metadatakatalogen/GetMetaDataById?id=c6b02e88-8084-4b3f-8a7d-33e5d45349c4","zoom":13,"latitude":59.16786586448691,"longitude":17.592748405764738,"data":{"type":"Feature","properties":{"NVRID":"2003326","NAMN":"Hovsjö 1:1","SKYDDSTYP":"Naturminne","BESLSTATUS":"Gällande","URSBESLDAT":"1951/02/21","URSGALLDAT":"1951/02/21","SENGALLDAT":"1951/02/21","LAN":"Stockholms Län","KOMMUN":"Södertälje","FORVALTARE":"Länsstyrelsen i Stockholms län","AREA_HA":0,"LAND_HA":0,"VATTEN_HA":0,"SKOG_HA":0,"GEOSTATUS":"Ospecificerad","DIARIENR":"63/462 BD 77     RrAB 86","LAGRUM":"Lag om naturminnesmärken från 1909","BESLMYND":"Länsstyrelse"},"geometry":{"type":"MultiPoint","coordinates":[[17.59312243204966,59.16779761489741],[17.593110129930025,59.16773015123576],[17.59274362788201,59.167942573071144],[17.592748405764738,59.16786586448691],[17.592578326227105,59.16797190191793],[17.592573874002245,59.167886302976655]]}}}