{"license":"CC0-1.0","description":{"sv":"2004094 (W-id) En tårgran (Lennheden)"},"sources":"Naturvårdsverket (Swedish Environmental Protection Agency), https://metadatakatalogen.naturvardsverket.se/metadatakatalogen/GetMetaDataById?id=c6b02e88-8084-4b3f-8a7d-33e5d45349c4","zoom":13,"latitude":60.52683850555812,"longitude":15.268621061981982,"data":{"type":"Feature","properties":{"NVRID":"2004320","NAMN":"2004094 (W-id) En tårgran (Lennheden)","SKYDDSTYP":"Naturminne","BESLSTATUS":"Gällande","URSBESLDAT":"1954/11/08","URSGALLDAT":"1954/11/08","SENGALLDAT":"1954/11/08","LAN":"Dalarnas Län","KOMMUN":"Borlänge","FORVALTARE":"Länsstyrelsen i Dalarnas län","AREA_HA":0,"LAND_HA":0,"VATTEN_HA":0,"SKOG_HA":0,"GEOSTATUS":"Ospecificerad","DIARIENR":"E/52 N 2","LAGRUM":"Naturskyddslagen","BESLMYND":"Länsstyrelse"},"geometry":{"type":"MultiPoint","coordinates":[[15.268621061981982,60.52683850555812]]}}}