{"license":"CC0-1.0","description":{"sv":"6 tallar, Västra Tiveden"},"sources":"Naturvårdsverket (Swedish Environmental Protection Agency), https://metadatakatalogen.naturvardsverket.se/metadatakatalogen/GetMetaDataById?id=c6b02e88-8084-4b3f-8a7d-33e5d45349c4","zoom":13,"latitude":58.99778068848792,"longitude":14.682359478283972,"data":{"type":"Feature","properties":{"NVRID":"2004068","NAMN":"6 tallar, Västra Tiveden","SKYDDSTYP":"Naturminne","BESLSTATUS":"Gällande","URSBESLDAT":"1934/12/20","URSGALLDAT":"1934/12/20","SENGALLDAT":"1934/12/20","LAN":"Örebro Län","KOMMUN":"Laxå","FORVALTARE":"Länsstyrelsen i Örebro län","AREA_HA":0,"LAND_HA":0,"VATTEN_HA":0,"SKOG_HA":0,"GEOSTATUS":"Ospecificerad","DIARIENR":"ed 129/1934, RrT 27","LAGRUM":"Lag om naturminnesmärken från 1909","BESLMYND":"Länsstyrelse"},"geometry":{"type":"MultiPoint","coordinates":[[14.682359478283972,58.99778068848792]]}}}