{"license":"CC0-1.0","description":{"sv":"2004146 (W-id) Skogsfrulokalen i Äppelbo"},"sources":"Naturvårdsverket (Swedish Environmental Protection Agency), https://metadatakatalogen.naturvardsverket.se/metadatakatalogen/GetMetaDataById?id=c6b02e88-8084-4b3f-8a7d-33e5d45349c4","zoom":13,"latitude":60.5473148928914,"longitude":14.018554296974198,"data":{"type":"Feature","properties":{"NVRID":"2004368","NAMN":"2004146 (W-id) Skogsfrulokalen i Äppelbo","SKYDDSTYP":"Naturminne","BESLSTATUS":"Gällande","URSBESLDAT":"1979/05/21","URSGALLDAT":"1979/05/21","SENGALLDAT":"1979/05/21","LAN":"Dalarnas Län","KOMMUN":"Vansbro","FORVALTARE":"Länsstyrelsen i Dalarnas län","AREA_HA":2.29,"LAND_HA":0,"VATTEN_HA":0,"SKOG_HA":0,"GEOSTATUS":"Justerad mot fastighetskarta","DIARIENR":"11.122-3846-75","LAGRUM":"Naturvårdslagen","BESLMYND":"Länsstyrelse"},"geometry":{"type":"MultiPolygon","coordinates":[[[[14.020399049164984,60.5470467952378],[14.018767123781991,60.54629378314288],[14.01696157694418,60.5472834133431],[14.016539242593385,60.547356044387556],[14.018932415463425,60.548473951761125],[14.019451399565702,60.54749486348841],[14.020399049164984,60.5470467952378]]]]}}}