{"license":"CC0-1.0","description":{"sv":"Ett bokträd"},"sources":"Naturvårdsverket (Swedish Environmental Protection Agency), https://metadatakatalogen.naturvardsverket.se/metadatakatalogen/GetMetaDataById?id=c6b02e88-8084-4b3f-8a7d-33e5d45349c4","zoom":13,"latitude":59.54202470246252,"longitude":16.756384864600314,"data":{"type":"Feature","properties":{"NVRID":"2005152","NAMN":"Ett bokträd","SKYDDSTYP":"Naturminne","BESLSTATUS":"Gällande","URSBESLDAT":"1925/05/06","URSGALLDAT":"1925/06/03","SENGALLDAT":"1925/06/03","LAN":"Västmanlands Län","KOMMUN":"Västerås","FORVALTARE":"Länsstyrelsen i Västmanlands län","AREA_HA":0,"LAND_HA":0,"VATTEN_HA":0,"SKOG_HA":0,"GEOSTATUS":"Ospecificerad","DIARIENR":"U 20,LST 14/102 1925","LAGRUM":"Lag om naturminnesmärken från 1909","BESLMYND":"Länsstyrelse"},"geometry":{"type":"MultiPoint","coordinates":[[16.756384864600314,59.54202470246252]]}}}