{"license":"CC0-1.0","description":{"sv":"En tall Arentorp 5:1"},"sources":"Naturvårdsverket (Swedish Environmental Protection Agency), https://metadatakatalogen.naturvardsverket.se/metadatakatalogen/GetMetaDataById?id=c6b02e88-8084-4b3f-8a7d-33e5d45349c4","zoom":13,"latitude":58.35546051223657,"longitude":16.647818867404496,"data":{"type":"Feature","properties":{"NVRID":"2011269","NAMN":"En tall Arentorp 5:1","SKYDDSTYP":"Naturminne","BESLSTATUS":"Gällande","URSBESLDAT":"1946/09/30","URSGALLDAT":"1946/09/30","SENGALLDAT":"1946/09/30","LAN":"Östergötlands Län","KOMMUN":"Söderköping","FORVALTARE":"Länsstyrelsen i Östergötlands län","AREA_HA":0,"LAND_HA":0,"VATTEN_HA":0,"SKOG_HA":0,"GEOSTATUS":"Ospecificerad","DIARIENR":"nr 82 ensk.pers./1944, Rr 56","LAGRUM":"Lag om naturminnesmärken från 1909","BESLMYND":"Länsstyrelse"},"geometry":{"type":"MultiPoint","coordinates":[[16.647818867404496,58.35546051223657]]}}}