{"license":"CC0-1.0","description":{"sv":"Gullyckeskär, Oppmanna"},"sources":"Naturvårdsverket (Swedish Environmental Protection Agency), https://metadatakatalogen.naturvardsverket.se/metadatakatalogen/GetMetaDataById?id=c6b02e88-8084-4b3f-8a7d-33e5d45349c4","zoom":13,"latitude":56.14594905599294,"longitude":14.335925167749664,"data":{"type":"Feature","properties":{"NVRID":"2012157","NAMN":"Gullyckeskär, Oppmanna","SKYDDSTYP":"Naturminne","BESLSTATUS":"Gällande","URSBESLDAT":"1935/04/08","URSGALLDAT":"1935/04/08","SENGALLDAT":"1935/04/08","LAN":"Skåne Län","KOMMUN":"Kristianstad","FORVALTARE":"Länsstyrelsen i Skåne län","AREA_HA":0.16,"LAND_HA":0.16,"VATTEN_HA":0,"SKOG_HA":0,"GEOSTATUS":"Ospecificerad","DIARIENR":"927/1 1934","LAGRUM":"Lag om naturminnesmärken från 1909","BESLMYND":"Länsstyrelse"},"geometry":{"type":"MultiPolygon","coordinates":[[[[14.33619025192646,56.14615889883416],[14.336387723107354,56.14593283756998],[14.335960873993855,56.14577841142685],[14.33568761326593,56.14572245803973],[14.335476300227555,56.14602390844841],[14.33619025192646,56.14615889883416]]]]}}}