{"license":"CC0-1.0","description":{"sv":"Krakvät"},"sources":"Naturvårdsverket (Swedish Environmental Protection Agency), https://metadatakatalogen.naturvardsverket.se/metadatakatalogen/GetMetaDataById?id=2921b01a-0baf-4702-a89f-9c5626c97844","zoom":13,"latitude":57.15590804801701,"longitude":18.181010961854835,"data":{"type":"Feature","properties":{"NVRID":"2000429","NAMN":"Krakvät","SKYDDSTYP":"Naturreservat","BESLSTATUS":"Gällande","URSBESLDAT":"1998/03/18","URSGALLDAT":"1998/05/26","SENGALLDAT":"1998/05/26","LAN":"Gotlands Län","KOMMUN":"Gotland","IUCNKAT":"IV, Habitat/Artskyddsområde (Habitat/Species Management Area)","FORVALTARE":"Länsstyrelsen i Gotlands län","AREA_HA":16.39,"LAND_HA":16.39,"VATTEN_HA":0,"SKOG_HA":7.387,"GEOSTATUS":"Slutligt inmätt","DIARIENR":"231-2931-95","LAGRUM":"Naturvårdslagen","BESLMYND":"Länsstyrelse"},"geometry":{"type":"MultiPolygon","coordinates":[[[[18.17977230874749,57.1592050389227],[18.185765196507763,57.15487667900818],[18.180772571573165,57.15333114630016],[18.179534954037422,57.15429771853613],[18.180283849999736,57.155295311412495],[18.177301757166962,57.154569597525175],[18.17685764713833,57.154898117862984],[18.17977230874749,57.1592050389227]]]]}}}